CHANGES.txt
DEPENDENCES.txt
README.txt
setup.py
src/pd/__init__.py
src/pd.requires.rpm.egg-info/PKG-INFO
src/pd.requires.rpm.egg-info/SOURCES.txt
src/pd.requires.rpm.egg-info/dependency_links.txt
src/pd.requires.rpm.egg-info/namespace_packages.txt
src/pd.requires.rpm.egg-info/requires.txt
src/pd.requires.rpm.egg-info/top_level.txt
src/pd.requires.rpm.egg-info/zip-safe
src/pd/requires/__init__.py
src/pd/requires/rpm/__init__.py
src/pd/requires/rpm/pd.requires.rpm.txt
src/pd/requires/rpm/rpmdriver.py
src/pd/requires/rpm/rpmdriver_lazy.py
