Metadata-Version: 1.0
Name: pd.requires.rpm
Version: 0.0.2
Summary: Requires/Provides source from installed rpm database
Home-page: http://www.dreambot.ru/product/DreamBotOtherReleases/pd.requires.rpm
Author: Andrey Orlov
Author-email: dbdt@dreambot.ru
License: GPL v2.1
Platform: UNKNOWN
Classifier: Intended Audience :: Developers
Classifier: License :: OSI Approved :: GNU General Public License (GPL)
Classifier: Programming Language :: Python
Classifier: Operating System :: OS Independent
